create_initial_superuser/__init__.py
create_initial_superuser/apps.py
create_initial_superuser/backends.py
django_create_initial_user-1.2.3.dist-info/METADATA
django_create_initial_user-1.2.3.dist-info/WHEEL
django_create_initial_user-1.2.3.dist-info/licenses/LICENSE
django_create_initial_user-1.2.3.dist-info/RECORD
