Metadata-Version: 2.4
Name: django-create-initial-user
Version: 1.2.3
Summary: Django authentication backend that automatically creates a superuser on first login
Project-URL: Homepage, https://github.com/rsp2k/django-create-initial-user
Project-URL: Repository, https://github.com/rsp2k/django-create-initial-user
Project-URL: Issues, https://github.com/rsp2k/django-create-initial-user/issues
Project-URL: Changelog, https://github.com/rsp2k/django-create-initial-user/blob/main/CHANGELOG.md
Author-email: Ryan Malloy <ryan@supported.systems>
License: MIT License
License-File: LICENSE
Keywords: authentication,backend,django,superuser
Classifier: Development Status :: 4 - Beta
Classifier: Framework :: Django
Classifier: Framework :: Django :: 3.2
Classifier: Framework :: Django :: 4.0
Classifier: Framework :: Django :: 4.1
Classifier: Framework :: Django :: 4.2
Classifier: Framework :: Django :: 5.0
Classifier: Intended Audience :: Developers
Classifier: Operating System :: OS Independent
Classifier: Programming Language :: Python
Classifier: Programming Language :: Python :: 3
Classifier: Programming Language :: Python :: 3.9
Classifier: Programming Language :: Python :: 3.10
Classifier: Programming Language :: Python :: 3.11
Classifier: Programming Language :: Python :: 3.12
Classifier: Topic :: Internet :: WWW/HTTP
Classifier: Topic :: Software Development :: Libraries :: Python Modules
Requires-Python: >=3.9
Requires-Dist: django>=4.2
Provides-Extra: dev
Requires-Dist: autoflake>=2.2; extra == 'dev'
Requires-Dist: bandit>=1.7; extra == 'dev'
Requires-Dist: black>=23.12; extra == 'dev'
Requires-Dist: coverage>=7.0; extra == 'dev'
Requires-Dist: django-stubs>=4.2; extra == 'dev'
Requires-Dist: flake8>=7.0; extra == 'dev'
Requires-Dist: isort>=5.13; extra == 'dev'
Requires-Dist: mypy>=1.8; extra == 'dev'
Requires-Dist: pre-commit>=3.6; extra == 'dev'
Requires-Dist: pyupgrade>=3.15; extra == 'dev'
Requires-Dist: safety>=2.3; extra == 'dev'
Provides-Extra: test
Requires-Dist: coverage>=7.0; extra == 'test'
